odoo/addons/account_avatax_sale_oca/README.rst
odoo/addons/account_avatax_sale_oca/__init__.py
odoo/addons/account_avatax_sale_oca/__manifest__.py
odoo/addons/account_avatax_sale_oca/i18n/account_avatax_sale.pot
odoo/addons/account_avatax_sale_oca/i18n/account_avatax_sale_oca.pot
odoo/addons/account_avatax_sale_oca/models/__init__.py
odoo/addons/account_avatax_sale_oca/models/account_move.py
odoo/addons/account_avatax_sale_oca/models/avalara_salestax.py
odoo/addons/account_avatax_sale_oca/models/partner.py
odoo/addons/account_avatax_sale_oca/models/sale_order.py
odoo/addons/account_avatax_sale_oca/readme/CONTRIBUTORS.rst
odoo/addons/account_avatax_sale_oca/readme/DESCRIPTION.rst
odoo/addons/account_avatax_sale_oca/readme/USAGE.rst
odoo/addons/account_avatax_sale_oca/static/description/icon.png
odoo/addons/account_avatax_sale_oca/static/description/index.html
odoo/addons/account_avatax_sale_oca/views/avalara_salestax_view.xml
odoo/addons/account_avatax_sale_oca/views/partner_view.xml
odoo/addons/account_avatax_sale_oca/views/sale_order_view.xml
odoo14_addon_account_avatax_sale_oca-14.0.2.0.0.dist-info/METADATA
odoo14_addon_account_avatax_sale_oca-14.0.2.0.0.dist-info/WHEEL
odoo14_addon_account_avatax_sale_oca-14.0.2.0.0.dist-info/top_level.txt
odoo14_addon_account_avatax_sale_oca-14.0.2.0.0.dist-info/RECORD
